prompt_cli_rush-0.1.0.dist-info/licenses/LICENSE
promptkit/__init__.py
promptkit/cli.py
promptkit/core.py
prompt_cli_rush-0.1.0.dist-info/METADATA
prompt_cli_rush-0.1.0.dist-info/WHEEL
prompt_cli_rush-0.1.0.dist-info/entry_points.txt
prompt_cli_rush-0.1.0.dist-info/top_level.txt
prompt_cli_rush-0.1.0.dist-info/RECORD
